{
  "project_info": {
    "project_number": "59777583948",
    "firebase_url": "https://instagram-81214-default-rtdb.asia-southeast1.firebasedatabase.app",
    "project_id": "instagram-81214",
    "storage_bucket": "instagram-81214.appspot.com"
  },
  "client": [
    {
      "client_info": {
        "mobilesdk_app_id": "1:59777583948:android:34188a639585c1a5679de9",
        "android_client_info": {
          "package_name": "com.ins.instagram_g3"
        }
      },
      "oauth_client": [
        {
          "client_id": "59777583948-b9gnn4utep1rsjoe8kq72s0b36sqgk28.apps.googleusercontent.com",
          "client_type": 1,
          "android_info": {
            "package_name": "com.ins.instagram_g3",
            "certificate_hash": "f57c59e28e7f52c4b5cee3750ebd0d9822b19521"
          }
        },
        {
          "client_id": "59777583948-fjo70d52utgfs9if83pdg02tmh5sitt5.apps.googleusercontent.com",
          "client_type": 3
        }
      ],
      "api_key": [
        {
          "current_key": "AIzaSyBQBz6MRv4xo_uO4YpKcbmLULJTmIf1Wq0"
        }
      ],
      "services": {
        "appinvite_service": {
          "other_platform_oauth_client": [
            {
              "client_id": "59777583948-fjo70d52utgfs9if83pdg02tmh5sitt5.apps.googleusercontent.com",
              "client_type": 3
            }
          ]
        }
      }
    }
  ],
  "configuration_version": "1"
}